mdformat_pyproject/__init__.py
mdformat_pyproject/plugin.py
mdformat_pyproject-0.0.2.dist-info/entry_points.txt
mdformat_pyproject-0.0.2.dist-info/LICENSE
mdformat_pyproject-0.0.2.dist-info/WHEEL
mdformat_pyproject-0.0.2.dist-info/METADATA
mdformat_pyproject-0.0.2.dist-info/RECORD
