Metadata-Version: 2.3
Name: mdformat_pyproject
Version: 0.0.2
Summary: An mdformat plugin for...
Keywords: mdformat,markdown,markdown-it
Author-email: Carles Sala <csala@csail.mit.com>
Requires-Python: >=3.7
Classifier: Intended Audience :: Developers
Classifier: License :: OSI Approved :: MIT License
Classifier: Programming Language :: Python :: 3
Classifier: Topic :: Software Development :: Libraries :: Python Modules
Requires-Dist: mdformat ~=0.7
Requires-Dist: tomli ~=2.0; python_version < '3.11'
Requires-Dist: pre-commit ; extra == "dev"
Requires-Dist: pytest~=6.0 ; extra == "test"
Requires-Dist: coverage ; extra == "test"
Requires-Dist: pytest-cov ; extra == "test"
Project-URL: Homepage, https://github.com/csala/mdformat-pyproject
Provides-Extra: dev
Provides-Extra: test
